h5forest/__init__.py
h5forest/_version.py
h5forest/config.py
h5forest/dataset_prompts.py
h5forest/errors.py
h5forest/fuzzy.py
h5forest/h5_forest.py
h5forest/node.py
h5forest/plotting.py
h5forest/progress.py
h5forest/styles.py
h5forest/tree.py
h5forest/utils.py
h5forest/bindings/__init__.py
h5forest/bindings/bindings.py
h5forest/bindings/dataset_funcs.py
h5forest/bindings/hist_funcs.py
h5forest/bindings/jump_funcs.py
h5forest/bindings/normal_funcs.py
h5forest/bindings/plot_funcs.py
h5forest/bindings/search_funcs.py
h5forest/bindings/tree_funcs.py
h5forest/bindings/utils.py
h5forest/bindings/window_funcs.py
h5forest/data/default_config.yaml
h5forest-1.0.2.dist-info/LICENSE
h5forest-1.0.2.dist-info/METADATA
h5forest-1.0.2.dist-info/WHEEL
h5forest-1.0.2.dist-info/entry_points.txt
h5forest-1.0.2.dist-info/top_level.txt
h5forest-1.0.2.dist-info/RECORD
