Metadata-Version: 2.1
Name: h5forest
Version: 1.0.2
Summary: A tool to view HDF5 file structures in the terminal.
Author-email: Will Roper <w.roper@sussex.ac.uk>
License: GNU GENERAL PUBLIC LICENSE
Project-URL: Homepage, https://github.com/WillJRoper/h5forest
Project-URL: Repository, https://github.com/WillJRoper/h5forest
Project-URL: Documentation, https://willjroper.github.io/h5forest/
Classifier: Development Status :: 5 - Production/Stable
Classifier: Intended Audience :: Science/Research
Classifier: License :: OSI Approved :: GNU General Public License v3 (GPLv3)
Classifier: Programming Language :: Python :: 3
Classifier: Programming Language :: Python :: 3.9
Classifier: Programming Language :: Python :: 3.10
Classifier: Programming Language :: Python :: 3.11
Classifier: Programming Language :: Python :: 3.12
Classifier: Programming Language :: Python :: 3.13
Classifier: Topic :: Scientific/Engineering
Classifier: Environment :: Console
Requires-Python: >=3.9
License-File: LICENSE
Requires-Dist: h5py
Requires-Dist: numpy
Requires-Dist: prompt-toolkit
Requires-Dist: matplotlib
Requires-Dist: rapidfuzz >=3.0.0
Requires-Dist: pyyaml >=5.0
Requires-Dist: ruamel.yaml >=0.18
Provides-Extra: dev
Requires-Dist: ruff ; extra == 'dev'
Provides-Extra: docs
Requires-Dist: mkdocs >=1.5.0 ; extra == 'docs'
Requires-Dist: mkdocs-material >=9.0.0 ; extra == 'docs'
Requires-Dist: mkdocs-material[imaging] ; extra == 'docs'
Provides-Extra: hdf5plugin
Requires-Dist: hdf5plugin ; extra == 'hdf5plugin'
Provides-Extra: test
Requires-Dist: pytest >=6.0 ; extra == 'test'
Requires-Dist: pytest-cov >=2.0 ; extra == 'test'
Requires-Dist: pytest-mock >=3.0 ; extra == 'test'
Requires-Dist: h5py ; extra == 'test'
